is_int_even
