Metadata-Version: 2.1
Name: is-int-even
Version: 0.0.2
Summary: Is a number even?
Home-page: https://github.com/sifte/is-int-even
Author: sifte
Maintainer: sifte
License: MIT
Project-URL: Github, https://github.com/sifte/is-int-even
Keywords: even number
Platform: UNKNOWN
